backlib/__init__.py
backlib/internal/__init__.py
backlib/internal/backports/__init__.py
backlib/internal/backports/py310/__init__.py
backlib/internal/backports/py310/builtins/__init__.py
backlib/internal/backports/py310/builtins/internal/__init__.py
backlib/internal/backports/py310/builtins/internal/builtins.py
backlib/internal/backports/py310/errno/__init__.py
backlib/internal/backports/py310/errno/internal/__init__.py
backlib/internal/backports/py310/errno/internal/darwin1.py
backlib/internal/backports/py310/errno/internal/errno.py
backlib/internal/backports/py310/errno/internal/freebsd13.py
backlib/internal/backports/py310/errno/internal/msvc22.py
backlib/internal/backports/py310/errno/internal/posix88.py
backlib/internal/backports/py310/errno/internal/solaris10.py
backlib/internal/backports/py310/json.py
backlib/internal/backports/py310/operator.py
backlib/internal/backports/py310/os/__init__.py
backlib/internal/backports/py310/os/internal/__init__.py
backlib/internal/backports/py310/os/internal/linux5.py
backlib/internal/backports/py310/os/internal/os.py
backlib/internal/backports/py310/os_path/__init__.py
backlib/internal/backports/py310/os_path/internal/__init__.py
backlib/internal/backports/py310/os_path/internal/os_path.py
backlib/internal/backports/py310/os_path/internal/posixpath.py
backlib/internal/backports/py310/stat/__init__.py
backlib/internal/backports/py310/stat/internal/__init__.py
backlib/internal/backports/py310/stat/internal/stat.py
backlib/internal/backports/py311/__init__.py
backlib/internal/backports/py311/builtins.py
backlib/internal/backports/py311/errno/__init__.py
backlib/internal/backports/py311/errno/internal/__init__.py
backlib/internal/backports/py311/errno/internal/darwin1.py
backlib/internal/backports/py311/errno/internal/errno.py
backlib/internal/backports/py311/errno/internal/freebsd13.py
backlib/internal/backports/py311/json.py
backlib/internal/backports/py311/operator/__init__.py
backlib-0.2.2.dist-info/AUTHORS
backlib-0.2.2.dist-info/LICENSE
backlib-0.2.2.dist-info/METADATA
backlib-0.2.2.dist-info/WHEEL
backlib-0.2.2.dist-info/RECORD
