Metadata-Version: 2.3
Name: backlib
Version: 0.2.2
Summary: Backports for the Python standard library.
License: MIT
Keywords: python,backport,stdlib,errno,io,json,operator,os,os.path,stat,tomllib
Author: Sergei Y. Bogdanov
Author-email: syubogdanov@outlook.com
Maintainer: Sergei Y. Bogdanov
Maintainer-email: syubogdanov@outlook.com
Requires-Python: >=3.9,<3.14
Classifier: Development Status :: 2 - Pre-Alpha
Classifier: Intended Audience :: Developers
Classifier: License :: OSI Approved :: MIT License
Classifier: Operating System :: OS Independent
Classifier: Programming Language :: Python
Classifier: Programming Language :: Python :: 3
Classifier: Programming Language :: Python :: 3.9
Classifier: Programming Language :: Python :: 3.10
Classifier: Programming Language :: Python :: 3.11
Classifier: Programming Language :: Python :: 3.12
Classifier: Programming Language :: Python :: 3.13
Requires-Dist: typing-extensions (>=4.12,<5.0)
Project-URL: Documentation, https://backlib.readthedocs.io
Project-URL: Homepage, https://github.com/syubogdanov/backlib
Project-URL: Repository, https://github.com/syubogdanov/backlib
